{"nodes": [{"id": "members_createmembersinternalhandlers", "label": "createMembersInternalHandlers", "file_type": "code", "source_file": "src/server/internal/members.ts", "source_location": null, "source_url": null, "captured_at": null, "author": null, "contributor": null}], "edges": [{"source": "members_createmembersinternalhandlers", "target": "cors_getinternalcorsheaders", "relation": "calls", "confidence": "EXTRACTED", "confidence_score": 1.0, "source_file": "src/server/internal/members.ts", "source_location": null, "weight": 1.0}, {"source": "members_createmembersinternalhandlers", "target": "shared_actor_resolvesharedactor", "relation": "calls", "confidence": "EXTRACTED", "confidence_score": 1.0, "source_file": "src/server/internal/members.ts", "source_location": null, "weight": 1.0}, {"source": "members_createmembersinternalhandlers", "target": "internal_destructive_operation_gate", "relation": "implements", "confidence": "EXTRACTED", "confidence_score": 1.0, "source_file": "src/server/internal/members.ts", "source_location": null, "weight": 1.0}, {"source": "members_createmembersinternalhandlers", "target": "auth_createauthinternalhandlers", "relation": "semantically_similar_to", "confidence": "INFERRED", "confidence_score": 0.85, "source_file": "src/server/internal/members.ts", "source_location": null, "weight": 1.0}], "hyperedges": []}